randomisedString.py
randomisedstring-1.4.1.dist-info/METADATA
randomisedstring-1.4.1.dist-info/WHEEL
randomisedstring-1.4.1.dist-info/top_level.txt
randomisedstring-1.4.1.dist-info/RECORD
