Metadata-Version: 2.4
Name: randomisedString
Version: 1.4.1
Summary: A well maintained program to generate cryptographically safe randomised strings. Can be used for assigning unique IDs of any specified size. Can be alpha only or numeric or alphanumeric as specified.
Maintainer-email: Bhindi <bhaskarpanja93@gmail.com>
Project-URL: Homepage, https://github.com/BhaskarPanja93/randomisedString
Keywords: id,uid,uuid,random string,unique id
Classifier: License :: OSI Approved :: MIT License
Classifier: Programming Language :: Python
Classifier: Programming Language :: Python :: 3
Requires-Python: >=3.6
